{
  "active": false,
  "address": "0x6295Ab2BE04A617747481B292c390BfcA592Cf28",
  "color": null,
  "decimals": 18,
  "description": [],
  "id": "26cac123-a0e4-4d6f-abac-d934860b42d8",
  "links": {
    "explorer": "https://etherscan.io/token/0x6295Ab2BE04A617747481B292c390BfcA592Cf28",
    "research": null,
    "website": "https://www.tokendesk.io/"
  },
  "logo": {
    "png": {
      "url": "https://raw.githubusercontent.com/map3xyz/ethereum-tokenlist/master/0x6295ab2be04a617747481b292c390bfca592cf28/logo.png",
      "ipfs": null
    },
    "svg": {
      "url": null,
      "ipfs": null
    }
  },
  "name": "TokenDesk",
  "networkId": "ethereum",
  "spam": false,
  "symbol": "TDS",
  "tags": [],
  "verifications": [],
  "version": "0.0.1"
}