{
  "active": true,
  "address": "0x74658fB5f7fF3Bc7d70f7F792d53fd74f89dC055",
  "color": null,
  "decimals": 18,
  "description": null,
  "id": "6eb23e52-5d79-4612-8348-a35c7992fd81",
  "links": null,
  "logo": {
    "png": {
      "url": "https://raw.githubusercontent.com/map3xyz/ethereum-tokenlist/master/0x74658fB5f7fF3Bc7d70f7F792d53fd74f89dC055/logo.png",
      "ipfs": null
    },
    "svg": {
      "url": null,
      "ipfs": null
    }
  },
  "name": "MYTHIC",
  "networkId": "ethereum",
  "spam": true,
  "symbol": "MTCX",
  "tags": [],
  "verifications": [],
  "version": "0.0.1"
}