{
  "active": true,
  "address": "0x5403d3AC289322C482cD558014ea3888EF1B1d44",
  "color": null,
  "decimals": 8,
  "description": null,
  "id": "00ed751f-a6df-49d3-8d16-7b0118d1a3d1",
  "links": null,
  "logo": {
    "png": {
      "url": "https://raw.githubusercontent.com/map3xyz/ethereum-tokenlist/master/0x5403d3AC289322C482cD558014ea3888EF1B1d44/logo.png"
    }
  },
  "name": "Super Trip Chain",
  "networkId": "ethereum",
  "spam": false,
  "symbol": "SUPT",
  "tags": [],
  "type": "asset",
  "verifications": [],
  "version": "0.0.1"
}