{
  "active": true,
  "address": "0x48C589F9734289d8862a245Cf9884631a315696f",
  "color": null,
  "decimals": 8,
  "description": [],
  "id": "e8dfaff4-1f19-4bcb-b57d-a5867031218d",
  "links": {
    "explorer": "https://etherscan.io/token/0x48C589F9734289d8862a245Cf9884631a315696f",
    "research": null,
    "website": null
  },
  "logo": {
    "png": {
      "url": "https://raw.githubusercontent.com/map3xyz/ethereum-tokenlist/master/0x48c589f9734289d8862a245cf9884631a315696f/logo.png",
      "ipfs": null
    },
    "svg": {
      "url": null,
      "ipfs": null
    }
  },
  "name": "Coin Of King",
  "networkId": "ethereum",
  "spam": false,
  "symbol": "COK",
  "tags": [],
  "verifications": [],
  "version": "0.0.1"
}