{
  "active": true,
  "address": "0x1680Fc81D0B0Fd0B1A0ad3BEc3F75040cd7C19BC",
  "color": null,
  "decimals": 6,
  "description": null,
  "id": "48295efa-20e9-47d7-80af-0be4e3605272",
  "links": null,
  "logo": {
    "png": {
      "url": "https://raw.githubusercontent.com/map3xyz/ethereum-tokenlist/master/0x1680Fc81D0B0Fd0B1A0ad3BEc3F75040cd7C19BC/logo.png",
      "ipfs": null
    },
    "svg": {
      "url": null,
      "ipfs": null
    }
  },
  "name": "SMOOA",
  "networkId": "ethereum",
  "spam": true,
  "symbol": "SMO",
  "tags": [],
  "verifications": [],
  "version": "0.0.1"
}