{
  "active": false,
  "address": "0xdB209c97e0De799bbf14E3377307780Ddc26BE4E",
  "color": null,
  "decimals": 8,
  "description": [],
  "id": "cf82f942-56c4-4a42-a905-7076a0fa8106",
  "links": {
    "explorer": "https://etherscan.io/token/0xdB209c97e0De799bbf14E3377307780Ddc26BE4E",
    "research": null,
    "website": null
  },
  "logo": {
    "png": {
      "url": "https://raw.githubusercontent.com/map3xyz/ethereum-tokenlist/master/0xdb209c97e0de799bbf14e3377307780ddc26be4e/logo.png",
      "ipfs": null
    },
    "svg": {
      "url": null,
      "ipfs": null
    }
  },
  "name": "DarkPay Wallet",
  "networkId": "ethereum",
  "spam": false,
  "symbol": "DPW",
  "tags": [],
  "verifications": [],
  "version": "0.0.1"
}