{
  "active": false,
  "address": "0xf20E484056d9cb18733eAF6F2865257e23F92af1",
  "color": null,
  "decimals": 18,
  "description": [],
  "id": "327fc263-cadb-4da5-a26e-df257089a7a6",
  "links": {
    "explorer": "https://etherscan.io/token/0xf20E484056d9cb18733eAF6F2865257e23F92af1",
    "research": null,
    "website": null
  },
  "logo": {
    "png": {
      "url": "https://raw.githubusercontent.com/map3xyz/ethereum-tokenlist/master/0xf20e484056d9cb18733eaf6f2865257e23f92af1/logo.png",
      "ipfs": null
    },
    "svg": {
      "url": null,
      "ipfs": null
    }
  },
  "name": "Eterbase Cash",
  "networkId": "ethereum",
  "spam": false,
  "symbol": "XBASE",
  "tags": [],
  "verifications": [],
  "version": "0.0.1"
}