{
  "active": false,
  "address": "0x116a790417c31Ab790436A519D1C1F3353Edd4a2",
  "color": null,
  "decimals": 4,
  "description": [],
  "id": "021a29bb-eacc-49cb-a0f1-8bf6a5a43277",
  "links": {
    "explorer": "https://etherscan.io/token/0x116a790417c31Ab790436A519D1C1F3353Edd4a2",
    "research": null,
    "website": null
  },
  "logo": {
    "png": {
      "url": "https://raw.githubusercontent.com/map3xyz/ethereum-tokenlist/master/0x116a790417c31ab790436a519d1c1f3353edd4a2/logo.png",
      "ipfs": null
    },
    "svg": {
      "url": null,
      "ipfs": null
    }
  },
  "name": "Trip",
  "networkId": "ethereum",
  "spam": false,
  "symbol": "TRIP",
  "tags": [],
  "verifications": [],
  "version": "0.0.1"
}