{
  "active": true,
  "address": "0x6e8908cfa881C9f6f2C64d3436E7b80b1bf0093F",
  "color": null,
  "decimals": 18,
  "description": null,
  "id": "b43a2dcf-9332-4d35-b618-9e166bbd0b1e",
  "links": null,
  "logo": {
    "png": {
      "url": "https://raw.githubusercontent.com/map3xyz/ethereum-tokenlist/master/0x6e8908cfa881C9f6f2C64d3436E7b80b1bf0093F/logo.png",
      "ipfs": null
    },
    "svg": {
      "url": null,
      "ipfs": null
    }
  },
  "name": "Bistroo",
  "networkId": "ethereum",
  "spam": true,
  "symbol": "BIST",
  "tags": [],
  "verifications": [],
  "version": "0.0.1"
}