{
  "active": false,
  "address": "0x4943D17D370174D93b104E583F489175C22AD1b6",
  "color": null,
  "decimals": 0,
  "description": [],
  "id": "d073b2df-88ef-4c57-991d-85e98e1004bd",
  "links": {
    "explorer": "https://etherscan.io/token/0x4943D17D370174D93b104E583F489175C22AD1b6",
    "research": null,
    "website": null
  },
  "logo": {
    "png": {
      "url": "https://raw.githubusercontent.com/map3xyz/ethereum-tokenlist/master/0x4943d17d370174d93b104e583f489175c22ad1b6/logo.png",
      "ipfs": null
    },
    "svg": {
      "url": null,
      "ipfs": null
    }
  },
  "name": "EQR TESTmg21",
  "networkId": "ethereum",
  "spam": false,
  "symbol": "EQR",
  "tags": [],
  "verifications": [],
  "version": "0.0.1"
}