{
  "active": false,
  "address": "0x8efBADD950AC0910d92FCaE60cFD69D15e573Da0",
  "color": null,
  "decimals": 18,
  "description": [],
  "id": "9e350496-7a60-4a91-a591-2242edb5e53f",
  "links": {
    "explorer": "https://etherscan.io/token/0x8efBADD950AC0910d92FCaE60cFD69D15e573Da0",
    "research": null,
    "website": null
  },
  "logo": {
    "png": {
      "url": "https://raw.githubusercontent.com/map3xyz/ethereum-tokenlist/master/0x8efBADD950AC0910d92FCaE60cFD69D15e573Da0/logo.png",
      "ipfs": null
    },
    "svg": {
      "url": null,
      "ipfs": null
    }
  },
  "name": "CICBanking",
  "networkId": "ethereum",
  "spam": false,
  "symbol": "CIC",
  "tags": [],
  "verifications": [],
  "version": "0.0.1"
}