{
  "active": true,
  "address": "0x6C16119B20fa52600230F074b349dA3cb861a7e3",
  "color": null,
  "decimals": 18,
  "description": null,
  "id": "541592ef-6805-4896-bad9-e049145a6403",
  "links": null,
  "logo": {
    "png": {
      "url": "https://raw.githubusercontent.com/map3xyz/ethereum-tokenlist/master/0x6C16119B20fa52600230F074b349dA3cb861a7e3/logo.png",
      "ipfs": null
    },
    "svg": {
      "url": null,
      "ipfs": null
    }
  },
  "name": "Alkemi Network DAO Token",
  "networkId": "ethereum",
  "spam": true,
  "symbol": "ALK",
  "tags": [],
  "verifications": [],
  "version": "0.0.1"
}