{
  "active": true,
  "address": "0x1fc5EF0337AEA85C5f9198853a6E3A579a7A6987",
  "color": null,
  "decimals": 18,
  "description": {
    "en": "REAP CHAIN aims to solve Trilemma problem of existing blockchains based on PoDC consensus structure and implements a scalable platform to create a fair and transparent sharing economy ecosystem."
  },
  "id": "eefb965e-51e5-44cb-9b6c-6ab46ff77f70",
  "links": {
    "explorer": "https://etherscan.io/token/0x1fc5ef0337aea85c5f9198853a6e3a579a7a6987",
    "website": "https://reapchain.com/",
    "twitter": "https://twitter.com/ReapChain",
    "telegram": "https://t.me/joinchat/MbaQ7RaZchMzjAam9yMS0Q",
    "coinmarketcap": "https://coinmarketcap.com/currencies/reapchain/"
  },
  "logo": {
    "png": "https://raw.githubusercontent.com/map3xyz/ethereum-tokenlist/master/0x1fc5EF0337AEA85C5f9198853a6E3A579a7A6987/logo.png"
  },
  "name": "ReapChain",
  "networkCode": "ethereum",
  "spam": false,
  "symbol": "REAP",
  "tags": [],
  "type": "asset",
  "verifications": [],
  "version": "0.0.1"
}