{
  "active": true,
  "address": "0x253C7dd074f4BaCb305387F922225A4f737C08bd",
  "color": null,
  "decimals": 18,
  "description": null,
  "id": "b77eaff7-6f5f-4772-bd0e-dec27c5a7d1e",
  "links": null,
  "logo": {
    "png": {
      "url": "https://raw.githubusercontent.com/map3xyz/ethereum-tokenlist/master/0x253C7dd074f4BaCb305387F922225A4f737C08bd/logo.png",
      "ipfs": null
    },
    "svg": {
      "url": null,
      "ipfs": null
    }
  },
  "name": "LookRev",
  "networkId": "ethereum",
  "spam": true,
  "symbol": "LOOK",
  "tags": [],
  "verifications": [],
  "version": "0.0.1"
}