{
  "active": true,
  "address": "0x81Af4CB0A608839557834c1C275DD74BdEfb7Ec8",
  "color": null,
  "decimals": 18,
  "description": null,
  "id": "582f3665-dfc8-4f81-aea5-11c1a9d70f55",
  "links": null,
  "logo": {
    "png": {
      "url": "https://raw.githubusercontent.com/map3xyz/ethereum-tokenlist/master/0x81Af4CB0A608839557834c1C275DD74BdEfb7Ec8/logo.png",
      "ipfs": null
    },
    "svg": {
      "url": null,
      "ipfs": null
    }
  },
  "name": "NERBIO",
  "networkId": "ethereum",
  "spam": true,
  "symbol": "NRB",
  "tags": [],
  "verifications": [],
  "version": "0.0.1"
}