{
  "active": false,
  "address": "0xdbf0fac1499a931ed6e5F6122dbbCD3B80f66c7E",
  "color": null,
  "decimals": 8,
  "description": [],
  "id": "93c423cc-97e0-42d5-a6f8-3d7c07a44117",
  "links": {
    "explorer": "https://etherscan.io/token/0xdbf0fac1499a931ed6e5F6122dbbCD3B80f66c7E",
    "research": null,
    "website": null
  },
  "logo": {
    "png": {
      "url": "https://raw.githubusercontent.com/map3xyz/ethereum-tokenlist/master/0xdbf0fac1499a931ed6e5f6122dbbcd3b80f66c7e/logo.png",
      "ipfs": null
    },
    "svg": {
      "url": null,
      "ipfs": null
    }
  },
  "name": "RocketFuel",
  "networkId": "ethereum",
  "spam": false,
  "symbol": "RKFL",
  "tags": [],
  "verifications": [],
  "version": "0.0.1"
}