{
  "active": true,
  "address": "0xB813879550B7c7B7f59F83962e86e5fAA7E763a1",
  "color": null,
  "decimals": 18,
  "description": null,
  "id": "1503cee6-c39c-4b7b-90b9-a2b47092619d",
  "links": null,
  "logo": {
    "png": {
      "url": "https://raw.githubusercontent.com/map3xyz/ethereum-tokenlist/master/0xB813879550B7c7B7f59F83962e86e5fAA7E763a1/logo.png"
    }
  },
  "name": "BuidlersVault",
  "networkId": "ethereum",
  "spam": false,
  "symbol": "buidler",
  "tags": [],
  "type": "asset",
  "verifications": [],
  "version": "0.0.1"
}