{
  "active": true,
  "address": "0x865ec58b06bF6305B886793AA20A2da31D034E68",
  "color": null,
  "decimals": 18,
  "description": null,
  "id": "e911c93d-6c9f-4ea4-84e3-a53da3c0b30e",
  "links": null,
  "logo": {
    "png": {
      "url": "https://raw.githubusercontent.com/map3xyz/ethereum-tokenlist/master/0x865ec58b06bF6305B886793AA20A2da31D034E68/logo.png",
      "ipfs": null
    },
    "svg": {
      "url": null,
      "ipfs": null
    }
  },
  "name": "Moss Coin",
  "networkId": "ethereum",
  "spam": true,
  "symbol": "MOC",
  "tags": [],
  "verifications": [],
  "version": "0.0.1"
}