{
  "active": true,
  "address": "0x00c83aeCC790e8a4453e5dD3B0B4b3680501a7A7",
  "color": null,
  "decimals": 18,
  "description": null,
  "id": "87bbee88-2f2c-4931-a026-7a4277e51298",
  "links": null,
  "logo": {
    "png": {
      "url": "https://raw.githubusercontent.com/map3xyz/ethereum-tokenlist/master/0x00c83aeCC790e8a4453e5dD3B0B4b3680501a7A7/logo.png",
      "ipfs": null
    },
    "svg": {
      "url": null,
      "ipfs": null
    }
  },
  "name": "SKALE Network",
  "networkId": "ethereum",
  "spam": true,
  "symbol": "SKL",
  "tags": [],
  "verifications": [],
  "version": "0.0.1"
}