{
  "active": false,
  "address": "0x05cA0E11e7C183Dd01131Cd8Bb00c87464B7a285",
  "color": null,
  "decimals": 18,
  "description": [],
  "id": "9b6f7e93-e23c-405e-8ba0-979937cc1dc8",
  "links": {
    "explorer": "https://etherscan.io/token/0x05cA0E11e7C183Dd01131Cd8Bb00c87464B7a285",
    "research": null,
    "website": null
  },
  "logo": {
    "png": {
      "url": "https://raw.githubusercontent.com/map3xyz/ethereum-tokenlist/master/0x05ca0e11e7c183dd01131cd8bb00c87464b7a285/logo.png",
      "ipfs": null
    },
    "svg": {
      "url": null,
      "ipfs": null
    }
  },
  "name": "Entercoin",
  "networkId": "ethereum",
  "spam": false,
  "symbol": "ENTER",
  "tags": [],
  "verifications": [],
  "version": "0.0.1"
}