{
  "active": true,
  "address": "0xBfE03707aDb75b478Add9A01978057803F480E44",
  "color": null,
  "decimals": 8,
  "description": null,
  "id": "1832693b-ce7b-4770-8f4b-0c944b204df1",
  "links": null,
  "logo": {
    "png": {
      "url": "https://raw.githubusercontent.com/map3xyz/ethereum-tokenlist/master/0xBfE03707aDb75b478Add9A01978057803F480E44/logo.png",
      "ipfs": null
    },
    "svg": {
      "url": null,
      "ipfs": null
    }
  },
  "name": "IMSMART",
  "networkId": "ethereum",
  "spam": true,
  "symbol": "IMT",
  "tags": [],
  "verifications": [],
  "version": "0.0.1"
}