{
  "active": true,
  "address": "0xE51601f59A610DAc06868aa711A05e9a4e291256",
  "color": null,
  "decimals": 18,
  "description": [],
  "id": "5be35092-5645-4821-9047-31393fc5c668",
  "links": {
    "explorer": "https://etherscan.io/token/0xE51601f59A610DAc06868aa711A05e9a4e291256",
    "research": null,
    "website": null
  },
  "logo": {
    "png": {
      "url": "https://raw.githubusercontent.com/map3xyz/ethereum-tokenlist/master/0xe51601f59a610dac06868aa711a05e9a4e291256/logo.png",
      "ipfs": null
    },
    "svg": {
      "url": null,
      "ipfs": null
    }
  },
  "name": "TrueGoldCoin",
  "networkId": "ethereum",
  "spam": false,
  "symbol": "TGC",
  "tags": [],
  "verifications": [],
  "version": "0.0.1"
}