{
  "active": false,
  "address": "0x208bbb6bCEA22ef2011789331405347394EbAa51",
  "color": null,
  "decimals": 18,
  "description": [],
  "id": "606e5441-94d5-43f8-89a2-e7f5e9116524",
  "links": {
    "explorer": "https://etherscan.io/token/0x208bbb6bCEA22ef2011789331405347394EbAa51",
    "research": null,
    "website": "https://www.1ai.io/"
  },
  "logo": {
    "png": {
      "url": "https://raw.githubusercontent.com/map3xyz/ethereum-tokenlist/master/0x208bbb6bcea22ef2011789331405347394ebaa51/logo.png",
      "ipfs": null
    },
    "svg": {
      "url": null,
      "ipfs": null
    }
  },
  "name": "AI",
  "networkId": "ethereum",
  "spam": false,
  "symbol": "1AI",
  "tags": [],
  "verifications": [],
  "version": "0.0.1"
}