{
  "active": true,
  "address": "0xCb39C3502415152b2ec90ff07ee18cc94f681a72",
  "color": null,
  "decimals": 18,
  "description": null,
  "id": "e20e79bd-a2ea-4bc0-af35-d1c954058692",
  "links": null,
  "logo": {
    "png": {
      "url": "https://raw.githubusercontent.com/map3xyz/ethereum-tokenlist/master/0xCb39C3502415152b2ec90ff07ee18cc94f681a72/logo.png",
      "ipfs": null
    },
    "svg": {
      "url": null,
      "ipfs": null
    }
  },
  "name": "storeum",
  "networkId": "ethereum",
  "spam": true,
  "symbol": "STO",
  "tags": [],
  "verifications": [],
  "version": "0.0.1"
}