{
  "active": true,
  "address": "0x98626E2C9231f03504273d55f397409deFD4a093",
  "color": null,
  "decimals": 18,
  "description": [],
  "id": "e5b67830-cf42-4f72-8fff-3d3c8e371e2a",
  "links": {
    "explorer": "https://etherscan.io/token/0x98626E2C9231f03504273d55f397409deFD4a093",
    "research": null,
    "website": null
  },
  "logo": {
    "png": {
      "url": "https://raw.githubusercontent.com/map3xyz/ethereum-tokenlist/master/0x98626e2c9231f03504273d55f397409defd4a093/logo.png",
      "ipfs": null
    },
    "svg": {
      "url": null,
      "ipfs": null
    }
  },
  "name": "Dev",
  "networkId": "ethereum",
  "spam": false,
  "symbol": "DEV",
  "tags": [],
  "verifications": [],
  "version": "0.0.1"
}