{
  "active": false,
  "address": "0x06B4d381FFA099E47aFE7dda0a310d582023d063",
  "color": null,
  "decimals": 18,
  "description": [],
  "id": "d45c9804-e3a6-43b0-9b6b-1a10e179e35b",
  "links": {
    "explorer": "https://etherscan.io/token/0x06B4d381FFA099E47aFE7dda0a310d582023d063",
    "research": null,
    "website": null
  },
  "logo": {
    "png": {
      "url": "https://raw.githubusercontent.com/map3xyz/ethereum-tokenlist/master/0x06B4d381FFA099E47aFE7dda0a310d582023d063/logo.png",
      "ipfs": null
    },
    "svg": {
      "url": null,
      "ipfs": null
    }
  },
  "name": "Shine Share Coin",
  "networkId": "ethereum",
  "spam": false,
  "symbol": "SSC",
  "tags": [],
  "verifications": [],
  "version": "0.0.1"
}