{
  "active": true,
  "address": "0xc42209aCcC14029c1012fB5680D95fBd6036E2a0",
  "color": null,
  "decimals": 18,
  "description": null,
  "id": "c25ca189-b996-4870-8eff-3100adc95096",
  "links": null,
  "logo": {
    "png": {
      "url": "https://raw.githubusercontent.com/map3xyz/ethereum-tokenlist/master/0xc42209aCcC14029c1012fB5680D95fBd6036E2a0/logo.png",
      "ipfs": null
    },
    "svg": {
      "url": null,
      "ipfs": null
    }
  },
  "name": "PayPie",
  "networkId": "ethereum",
  "spam": true,
  "symbol": "PPP",
  "tags": [],
  "verifications": [],
  "version": "0.0.1"
}