{
  "active": true,
  "address": "0x3BeB004537DcDe3DA918C71a1e5065C5B4194910",
  "color": null,
  "decimals": 0,
  "description": null,
  "id": "b47e1e3b-af5f-490e-a4d8-cf8d33e30c5f",
  "links": null,
  "logo": {
    "png": {
      "url": "https://raw.githubusercontent.com/map3xyz/ethereum-tokenlist/master/0x3BeB004537DcDe3DA918C71a1e5065C5B4194910/logo.png",
      "ipfs": null
    },
    "svg": {
      "url": null,
      "ipfs": null
    }
  },
  "name": "CM - 0R818644",
  "networkId": "ethereum",
  "spam": true,
  "symbol": "CM",
  "tags": [],
  "verifications": [],
  "version": "0.0.1"
}