{
  "active": false,
  "address": "0x50398DE4651FFeCF38A93cc4dE9f2F0e20f3daD1",
  "color": null,
  "decimals": 6,
  "description": [],
  "id": "51687d96-7d8d-4fb7-99ce-56ab5a88ec98",
  "links": {
    "explorer": "https://etherscan.io/token/0x50398DE4651FFeCF38A93cc4dE9f2F0e20f3daD1",
    "research": null,
    "website": null
  },
  "logo": {
    "png": {
      "url": "https://raw.githubusercontent.com/map3xyz/ethereum-tokenlist/master/0x50398de4651ffecf38a93cc4de9f2f0e20f3dad1/logo.png",
      "ipfs": null
    },
    "svg": {
      "url": null,
      "ipfs": null
    }
  },
  "name": "PYR",
  "networkId": "ethereum",
  "spam": false,
  "symbol": "PYR",
  "tags": [],
  "verifications": [],
  "version": "0.0.1"
}