{
  "active": true,
  "address": "0xAD640689e6950b7453729A4686edB3FdfD754616",
  "color": null,
  "decimals": 18,
  "description": null,
  "id": "a3a702dc-b455-4e7e-83cd-1177cc77db88",
  "identifiers": {
    "coinmarketcap": 4743
  },
  "links": null,
  "logo": {
    "png": "https://raw.githubusercontent.com/map3xyz/ethereum-tokenlist/master/0xAD640689e6950b7453729A4686edB3FdfD754616/logo.png"
  },
  "name": "CIChain",
  "networkCode": "ethereum",
  "spam": false,
  "symbol": "CIC",
  "tags": [],
  "type": "asset",
  "verifications": [],
  "version": "0.0.1"
}