{
  "active": true,
  "address": "0x175D9Dfd6850AA96460E29bC0cEad05756965E91",
  "color": null,
  "decimals": 18,
  "description": [
    {
      "locale": "en",
      "value": "ERC20 version of the IOV token",
      "verified": true
    }
  ],
  "id": "8fa35a71-ad4b-4577-b33f-4777e24322e2",
  "links": {
    "explorer": "https://etherscan.io/token/0x175D9Dfd6850AA96460E29bC0cEad05756965E91",
    "research": null,
    "website": "https://starname.me/",
    "github": "https://github.com/iov-one",
    "twitter": "https://twitter.com/starname_me",
    "telegram": "https://t.me/internetofvalues",
    "medium": "https://medium.com/iov-internet-of-values"
  },
  "logo": {
    "png": {
      "url": "https://raw.githubusercontent.com/map3xyz/ethereum-tokenlist/master/0x175d9dfd6850aa96460e29bc0cead05756965e91/logo.png",
      "ipfs": null
    },
    "svg": {
      "url": null,
      "ipfs": null
    }
  },
  "name": "Starname (WIOV)",
  "networkId": "ethereum",
  "spam": false,
  "symbol": "WIOV",
  "tags": [],
  "verifications": [],
  "version": "0.0.1"
}