{
  "active": false,
  "address": "0xf7B098298f7C69Fc14610bf71d5e02c60792894C",
  "color": null,
  "decimals": 3,
  "description": [],
  "id": "34140c85-6067-4411-8775-19d08459faa9",
  "links": {
    "explorer": "https://etherscan.io/token/0xf7B098298f7C69Fc14610bf71d5e02c60792894C",
    "research": null,
    "website": "https://matchpool.co/"
  },
  "logo": {
    "png": {
      "url": "https://raw.githubusercontent.com/map3xyz/ethereum-tokenlist/master/0xf7b098298f7c69fc14610bf71d5e02c60792894c/logo.png",
      "ipfs": null
    },
    "svg": {
      "url": null,
      "ipfs": null
    }
  },
  "name": "Guppy",
  "networkId": "ethereum",
  "spam": false,
  "symbol": "GUP",
  "tags": [],
  "verifications": [],
  "version": "0.0.1"
}