{
  "active": false,
  "address": "0x1662CFFEFa08b150329E419b2F1a13D010174246",
  "color": null,
  "decimals": 18,
  "description": [],
  "id": "f9133f9d-d5da-45f4-89bd-7e750eb63ce3",
  "links": {
    "explorer": "https://etherscan.io/token/0x1662CFFEFa08b150329E419b2F1a13D010174246",
    "research": null,
    "website": null
  },
  "logo": {
    "png": {
      "url": "https://raw.githubusercontent.com/map3xyz/ethereum-tokenlist/master/0x1662cffefa08b150329e419b2f1a13d010174246/logo.png",
      "ipfs": null
    },
    "svg": {
      "url": null,
      "ipfs": null
    }
  },
  "name": "OxProtocol",
  "networkId": "ethereum",
  "spam": false,
  "symbol": "OXP",
  "tags": [],
  "verifications": [],
  "version": "0.0.1"
}