{
  "active": true,
  "address": "0xEa319e87Cf06203DAe107Dd8E5672175e3Ee976c",
  "color": null,
  "decimals": 18,
  "description": null,
  "id": "78746b39-8fb0-4e51-8f87-d509a32a14d2",
  "links": null,
  "logo": {
    "png": {
      "url": "https://raw.githubusercontent.com/map3xyz/ethereum-tokenlist/master/0xEa319e87Cf06203DAe107Dd8E5672175e3Ee976c/logo.png",
      "ipfs": null
    },
    "svg": {
      "url": null,
      "ipfs": null
    }
  },
  "name": "SURF Finance",
  "networkId": "ethereum",
  "spam": true,
  "symbol": "SURF",
  "tags": [],
  "verifications": [],
  "version": "0.0.1"
}