{
  "active": false,
  "address": "0xc074Dd87663b97097f06d805A164b6B271158738",
  "color": null,
  "decimals": 18,
  "description": [],
  "id": "82f42738-26a0-420f-883d-228c89af4cdd",
  "links": {
    "explorer": "https://etherscan.io/token/0xc074Dd87663b97097f06d805A164b6B271158738",
    "research": null,
    "website": null
  },
  "logo": {
    "png": {
      "url": "https://raw.githubusercontent.com/map3xyz/ethereum-tokenlist/master/0xc074Dd87663b97097f06d805A164b6B271158738/logo.png",
      "ipfs": null
    },
    "svg": {
      "url": null,
      "ipfs": null
    }
  },
  "name": "SOON TOKEN",
  "networkId": "ethereum",
  "spam": false,
  "symbol": "SOON",
  "tags": [],
  "verifications": [],
  "version": "0.0.1"
}