{
  "active": true,
  "address": "0xeE31F758b803b61Dfe2A56c6782C605d9131417e",
  "color": null,
  "decimals": 0,
  "description": null,
  "id": "9b5746b4-def3-4f5d-95df-f40587e451b1",
  "links": null,
  "logo": {
    "png": {
      "url": "https://raw.githubusercontent.com/map3xyz/ethereum-tokenlist/master/0xeE31F758b803b61Dfe2A56c6782C605d9131417e/logo.png",
      "ipfs": null
    },
    "svg": {
      "url": null,
      "ipfs": null
    }
  },
  "name": "CM - 0R916852",
  "networkId": "ethereum",
  "spam": true,
  "symbol": "CM",
  "tags": [],
  "verifications": [],
  "version": "0.0.1"
}