{
  "active": false,
  "address": "0xf2a7C7f3932EfCc2ECB6b2C372B84030dE191dB0",
  "color": null,
  "decimals": 18,
  "description": [],
  "id": "b310c162-829d-457f-8295-ffd7851abfa6",
  "links": {
    "explorer": "https://etherscan.io/token/0xf2a7C7f3932EfCc2ECB6b2C372B84030dE191dB0",
    "research": null,
    "website": null
  },
  "logo": {
    "png": {
      "url": "https://raw.githubusercontent.com/map3xyz/ethereum-tokenlist/master/0xf2a7c7f3932efcc2ecb6b2c372b84030de191db0/logo.png",
      "ipfs": null
    },
    "svg": {
      "url": null,
      "ipfs": null
    }
  },
  "name": "Secondary Data Attestation Token",
  "networkId": "ethereum",
  "spam": false,
  "symbol": "SEDA",
  "tags": [],
  "verifications": [],
  "version": "0.0.1"
}