{
  "active": true,
  "address": "0x8E9F8B93D049CbfeB37e0337b2d581ac6D0c3808",
  "color": null,
  "decimals": 0,
  "description": null,
  "id": "46f27da7-56a0-45d3-b304-6a11eb419502",
  "links": null,
  "logo": {
    "png": {
      "url": "https://raw.githubusercontent.com/map3xyz/ethereum-tokenlist/master/0x8E9F8B93D049CbfeB37e0337b2d581ac6D0c3808/logo.png",
      "ipfs": null
    },
    "svg": {
      "url": null,
      "ipfs": null
    }
  },
  "name": "IAM MDLT C 009-CN44",
  "networkId": "ethereum",
  "spam": true,
  "symbol": "IAM",
  "tags": [],
  "verifications": [],
  "version": "0.0.1"
}