{
  "active": true,
  "address": "0x4dB56A679DF2694c98793BdEB0a92f9C77C5ae64",
  "color": null,
  "decimals": 4,
  "description": null,
  "id": "75cf0d0f-86d0-4950-bca1-51ef76aea5ae",
  "links": null,
  "logo": {
    "png": {
      "url": "https://raw.githubusercontent.com/map3xyz/ethereum-tokenlist/master/0x4dB56A679DF2694c98793BdEB0a92f9C77C5ae64/logo.png",
      "ipfs": null
    },
    "svg": {
      "url": null,
      "ipfs": null
    }
  },
  "name": "KNIGHT",
  "networkId": "ethereum",
  "spam": true,
  "symbol": "KNIGHT",
  "tags": [],
  "verifications": [],
  "version": "0.0.1"
}