{
  "active": true,
  "address": "0xcF5A0010072ef3B791792F2D0Ea9A07ed84695d1",
  "color": null,
  "decimals": 8,
  "description": [],
  "id": "5793845d-7f1e-490f-9c35-f967a6af97e2",
  "links": {
    "explorer": "https://etherscan.io/token/0xcF5A0010072ef3B791792F2D0Ea9A07ed84695d1",
    "research": null,
    "website": null
  },
  "logo": {
    "png": {
      "url": "https://raw.githubusercontent.com/map3xyz/ethereum-tokenlist/master/0xcf5a0010072ef3b791792f2d0ea9a07ed84695d1/logo.png",
      "ipfs": null
    },
    "svg": {
      "url": null,
      "ipfs": null
    }
  },
  "name": "Krakatau Token",
  "networkId": "ethereum",
  "spam": false,
  "symbol": "KKT",
  "tags": [],
  "verifications": [],
  "version": "0.0.1"
}