{
  "active": false,
  "address": "0xdB096cC19b8227E2115855c5B39Dcc247470013C",
  "color": null,
  "decimals": 18,
  "description": [],
  "id": "f9f916a2-a6b5-4df8-b5e8-78eb32dc88c3",
  "links": {
    "explorer": "https://etherscan.io/token/0xdB096cC19b8227E2115855c5B39Dcc247470013C",
    "research": null,
    "website": "https://www.bitfex.com/"
  },
  "logo": {
    "png": {
      "url": "https://raw.githubusercontent.com/map3xyz/ethereum-tokenlist/master/0xdb096cc19b8227e2115855c5b39dcc247470013c/logo.png",
      "ipfs": null
    },
    "svg": {
      "url": null,
      "ipfs": null
    }
  },
  "name": "BITFEX",
  "networkId": "ethereum",
  "spam": false,
  "symbol": "BFX",
  "tags": [],
  "verifications": [],
  "version": "0.0.1"
}