{
  "active": true,
  "address": "0x076641aF1B8f06B7f8C92587156143C109002cbe",
  "color": null,
  "decimals": 18,
  "description": null,
  "id": "554d8ee6-9912-49f0-ab04-d921d3b6e889",
  "links": null,
  "logo": {
    "png": {
      "url": "https://raw.githubusercontent.com/map3xyz/ethereum-tokenlist/master/0x076641aF1B8f06B7f8C92587156143C109002cbe/logo.png",
      "ipfs": null
    },
    "svg": {
      "url": null,
      "ipfs": null
    }
  },
  "name": "SoPay",
  "networkId": "ethereum",
  "spam": true,
  "symbol": "SOP",
  "tags": [],
  "verifications": [],
  "version": "0.0.1"
}