{
  "active": true,
  "address": "0x4e7dE94e1243c25be42c523A0A4EA712BE6d9766",
  "color": null,
  "decimals": 8,
  "description": null,
  "id": "dee295aa-00e0-4812-a93c-64a761d0f650",
  "links": null,
  "logo": {
    "png": {
      "url": "https://raw.githubusercontent.com/map3xyz/ethereum-tokenlist/master/0x4e7dE94e1243c25be42c523A0A4EA712BE6d9766/logo.png"
    }
  },
  "name": "Roman Empire Club",
  "networkId": "ethereum",
  "spam": false,
  "symbol": "REC",
  "tags": [],
  "type": "asset",
  "verifications": [],
  "version": "0.0.1"
}