{
  "active": true,
  "address": "0x42d6622deCe394b54999Fbd73D108123806f6a18",
  "color": null,
  "decimals": 18,
  "description": [
    {
      "locale": "en",
      "value": "A cryptoeconomic powered adult entertainment ecosystem built on the Ethereum network.",
      "verified": true
    }
  ],
  "id": "cb807784-b558-4c18-98e7-f4a55f57b8bc",
  "links": {
    "explorer": "https://etherscan.io/token/0x42d6622deCe394b54999Fbd73D108123806f6a18",
    "research": null,
    "website": "https://spankchain.com/"
  },
  "logo": {
    "png": {
      "url": "https://raw.githubusercontent.com/map3xyz/ethereum-tokenlist/master/0x42d6622dece394b54999fbd73d108123806f6a18/logo.png",
      "ipfs": null
    },
    "svg": {
      "url": null,
      "ipfs": null
    }
  },
  "name": "SPANK",
  "networkId": "ethereum",
  "spam": false,
  "symbol": "SPANK",
  "tags": [],
  "verifications": [],
  "version": "0.0.1"
}