{
  "active": false,
  "address": "0x69F64d814Aa278825997e71738120392993973A4",
  "color": null,
  "decimals": 8,
  "description": [],
  "id": "12c60577-e393-47ff-9232-4e47abd5316d",
  "links": {
    "explorer": "https://etherscan.io/token/0x69F64d814Aa278825997e71738120392993973A4",
    "research": null,
    "website": null
  },
  "logo": {
    "png": {
      "url": "https://raw.githubusercontent.com/map3xyz/ethereum-tokenlist/master/0x69F64d814Aa278825997e71738120392993973A4/logo.png",
      "ipfs": null
    },
    "svg": {
      "url": null,
      "ipfs": null
    }
  },
  "name": "Crowdvilla Ownership",
  "networkId": "ethereum",
  "spam": false,
  "symbol": "CRV",
  "tags": [],
  "verifications": [],
  "version": "0.0.1"
}