{
  "active": true,
  "address": "0x76960Dccd5a1fe799F7c29bE9F19ceB4627aEb2f",
  "color": null,
  "decimals": 18,
  "description": null,
  "id": "b512cacd-913a-4083-830b-9669ed35a55e",
  "links": null,
  "logo": {
    "png": {
      "url": "https://raw.githubusercontent.com/map3xyz/ethereum-tokenlist/master/0x76960Dccd5a1fe799F7c29bE9F19ceB4627aEb2f/logo.png",
      "ipfs": null
    },
    "svg": {
      "url": null,
      "ipfs": null
    }
  },
  "name": "Red Community Token",
  "networkId": "ethereum",
  "spam": true,
  "symbol": "RED",
  "tags": [],
  "verifications": [],
  "version": "0.0.1"
}