{
  "active": true,
  "address": "0x70da48f4B7e83c386ef983D4CEF4e58c2c09D8Ac",
  "color": null,
  "decimals": 8,
  "description": [
    {
      "locale": "en",
      "value": "QURAS is a genuine secret contract platform that fulfills various privacy protection needs.",
      "verified": true
    }
  ],
  "id": "889e5858-1d1d-4e21-a71e-7598b2214236",
  "links": {
    "explorer": "https://etherscan.io/token/0x70da48f4B7e83c386ef983D4CEF4e58c2c09D8Ac",
    "research": null,
    "website": "https://quras.io/"
  },
  "logo": {
    "png": {
      "url": "https://raw.githubusercontent.com/map3xyz/ethereum-tokenlist/master/0x70da48f4B7e83c386ef983D4CEF4e58c2c09D8Ac/logo.png",
      "ipfs": null
    },
    "svg": {
      "url": null,
      "ipfs": null
    }
  },
  "name": "Quras Token",
  "networkId": "ethereum",
  "spam": false,
  "symbol": "XQC",
  "tags": [],
  "verifications": [],
  "version": "0.0.1"
}