{
  "active": false,
  "address": "0xd287beD5c9CdB8f8792b398Aa2A159E90e468FE8",
  "color": null,
  "decimals": 4,
  "description": [],
  "id": "1a1d01b2-c329-450a-b323-f620f19b4bc8",
  "links": {
    "explorer": "https://etherscan.io/token/0xd287beD5c9CdB8f8792b398Aa2A159E90e468FE8",
    "research": null,
    "website": null
  },
  "logo": {
    "png": {
      "url": "https://raw.githubusercontent.com/map3xyz/ethereum-tokenlist/master/0xd287bed5c9cdb8f8792b398aa2a159e90e468fe8/logo.png",
      "ipfs": null
    },
    "svg": {
      "url": null,
      "ipfs": null
    }
  },
  "name": "PYRAMIDOS",
  "networkId": "ethereum",
  "spam": false,
  "symbol": "PIR",
  "tags": [],
  "verifications": [],
  "version": "0.0.1"
}