{
  "active": true,
  "address": "0x6E605c269E0C92e70BEeB85486f1fC550f9380BD",
  "color": null,
  "decimals": 18,
  "description": null,
  "id": "844828ed-15f4-416d-80da-9b7a040bb703",
  "links": null,
  "logo": {
    "png": {
      "url": "https://raw.githubusercontent.com/map3xyz/ethereum-tokenlist/master/0x6E605c269E0C92e70BEeB85486f1fC550f9380BD/logo.png",
      "ipfs": null
    },
    "svg": {
      "url": null,
      "ipfs": null
    }
  },
  "name": "Catex",
  "networkId": "ethereum",
  "spam": true,
  "symbol": "CATT",
  "tags": [],
  "verifications": [],
  "version": "0.0.1"
}