{
  "active": true,
  "address": "0x6fe56C0bcdD471359019FcBC48863d6c3e9d4F41",
  "color": null,
  "decimals": 18,
  "description": [
    {
      "locale": "en",
      "value": " Props’ open-source infrastructure creates a decentralized network of apps operated by independent developers, who share an underlying token, benefiting from collective network effects.",
      "verified": true
    }
  ],
  "id": "3ebde2b0-b5eb-4689-b133-00fd3ab4134e",
  "links": {
    "explorer": "https://etherscan.io/token/0x6fe56C0bcdD471359019FcBC48863d6c3e9d4F41",
    "research": null,
    "website": "https://www.propsproject.com"
  },
  "logo": {
    "png": {
      "url": "https://raw.githubusercontent.com/map3xyz/ethereum-tokenlist/master/0x6fe56C0bcdD471359019FcBC48863d6c3e9d4F41/logo.png",
      "ipfs": null
    },
    "svg": {
      "url": null,
      "ipfs": null
    }
  },
  "name": "Props Token",
  "networkId": "ethereum",
  "spam": false,
  "symbol": "PROPS",
  "tags": [],
  "verifications": [],
  "version": "0.0.1"
}