{
  "active": true,
  "address": "0x7Bb09bC8aDE747178e95B1D035ecBeEBbB18cFee",
  "color": null,
  "decimals": 9,
  "description": null,
  "id": "e4d105df-01f6-400b-86f4-ac44695e23f3",
  "links": null,
  "logo": {
    "png": {
      "url": "https://raw.githubusercontent.com/map3xyz/ethereum-tokenlist/master/0x7Bb09bC8aDE747178e95B1D035ecBeEBbB18cFee/logo.png",
      "ipfs": null
    },
    "svg": {
      "url": null,
      "ipfs": null
    }
  },
  "name": "Crypto Valley Alliance",
  "networkId": "ethereum",
  "spam": true,
  "symbol": "CVA",
  "tags": [],
  "verifications": [],
  "version": "0.0.1"
}