{
  "active": false,
  "address": "0x18088625f914468A3Fcc5904cE24920a3ed87C1a",
  "color": null,
  "decimals": 18,
  "description": [],
  "id": "f72a3c13-4f83-4eb0-b359-47e39b4ab6d1",
  "links": {
    "explorer": "https://etherscan.io/token/0x18088625f914468A3Fcc5904cE24920a3ed87C1a",
    "research": null,
    "website": null
  },
  "logo": {
    "png": {
      "url": "https://raw.githubusercontent.com/map3xyz/ethereum-tokenlist/master/0x18088625f914468A3Fcc5904cE24920a3ed87C1a/logo.png",
      "ipfs": null
    },
    "svg": {
      "url": null,
      "ipfs": null
    }
  },
  "name": "GOOREO",
  "networkId": "ethereum",
  "spam": false,
  "symbol": "GOOREO",
  "tags": [],
  "verifications": [],
  "version": "0.0.1"
}