{
  "active": true,
  "address": "0xA3091381eB7e7c3c2cee5cb1578ADeBD3b7645EF",
  "color": null,
  "decimals": 18,
  "description": null,
  "id": "206879ee-69ac-4156-a495-d50d3704efb8",
  "links": null,
  "logo": {
    "png": {
      "url": "https://raw.githubusercontent.com/map3xyz/ethereum-tokenlist/master/0xA3091381eB7e7c3c2cee5cb1578ADeBD3b7645EF/logo.png"
    }
  },
  "name": "Digital Thai Baht",
  "networkId": "ethereum",
  "spam": false,
  "symbol": "THB",
  "tags": [],
  "type": "asset",
  "verifications": [],
  "version": "0.0.1"
}