{
  "active": false,
  "address": "0x9B70740e708a083C6fF38Df52297020f5DfAa5EE",
  "color": null,
  "decimals": 10,
  "description": [],
  "id": "6e0209f6-29f7-4a60-9a0f-1625c28a6593",
  "links": {
    "explorer": "https://etherscan.io/token/0x9B70740e708a083C6fF38Df52297020f5DfAa5EE",
    "research": null,
    "website": "https://daneel.io/"
  },
  "logo": {
    "png": {
      "url": "https://raw.githubusercontent.com/map3xyz/ethereum-tokenlist/master/0x9B70740e708a083C6fF38Df52297020f5DfAa5EE/logo.png",
      "ipfs": null
    },
    "svg": {
      "url": null,
      "ipfs": null
    }
  },
  "name": "Daneel",
  "networkId": "ethereum",
  "spam": false,
  "symbol": "DAN",
  "tags": [],
  "verifications": [],
  "version": "0.0.1"
}