{
  "active": false,
  "address": "0x5149fFdf642D551539f7B68Bd75fA37b16371eb9",
  "color": null,
  "decimals": 8,
  "description": [],
  "id": "34854122-3707-4101-b0a0-483a66d11b74",
  "links": {
    "explorer": "https://etherscan.io/token/0x5149fFdf642D551539f7B68Bd75fA37b16371eb9",
    "research": null,
    "website": null
  },
  "logo": {
    "png": {
      "url": "https://raw.githubusercontent.com/map3xyz/ethereum-tokenlist/master/0x5149ffdf642d551539f7b68bd75fa37b16371eb9/logo.png",
      "ipfs": null
    },
    "svg": {
      "url": null,
      "ipfs": null
    }
  },
  "name": "KhanhTest01",
  "networkId": "ethereum",
  "spam": false,
  "symbol": "KT1",
  "tags": [],
  "verifications": [],
  "version": "0.0.1"
}