{
  "active": true,
  "address": "0x922105fAd8153F516bCfB829f56DC097a0E1D705",
  "color": null,
  "decimals": 18,
  "description": null,
  "id": "b8a0944d-64d3-48e9-a257-4445b5756e20",
  "links": null,
  "logo": {
    "png": {
      "url": "https://raw.githubusercontent.com/map3xyz/ethereum-tokenlist/master/0x922105fAd8153F516bCfB829f56DC097a0E1D705/logo.png"
    }
  },
  "name": "Yee - A Blockchain-powered & Cloud-based Social Ecosystem",
  "networkId": "ethereum",
  "spam": false,
  "symbol": "YEE",
  "tags": [],
  "type": "asset",
  "verifications": [],
  "version": "0.0.1"
}