{
  "active": true,
  "address": "0x9a49f02e128a8E989b443a8f94843C0918BF45E7",
  "color": null,
  "decimals": 8,
  "description": null,
  "id": "519ea5ec-aed5-4cb0-8378-212d9c5933d9",
  "links": null,
  "logo": {
    "png": {
      "url": "https://raw.githubusercontent.com/map3xyz/ethereum-tokenlist/master/0x9a49f02e128a8E989b443a8f94843C0918BF45E7/logo.png",
      "ipfs": null
    },
    "svg": {
      "url": null,
      "ipfs": null
    }
  },
  "name": "TOKOK",
  "networkId": "ethereum",
  "spam": true,
  "symbol": "TOK",
  "tags": [],
  "verifications": [],
  "version": "0.0.1"
}